asciiconv/__init__.py
asciiconv/asciify.py
asciiconv-0.2.3.dist-info/LICENCE
asciiconv-0.2.3.dist-info/METADATA
asciiconv-0.2.3.dist-info/WHEEL
asciiconv-0.2.3.dist-info/top_level.txt
asciiconv-0.2.3.dist-info/RECORD
